dj-gravatar/__init__.py
dj-gravatar/settings.py
dj-gravatar/templatetags/__init__.py
dj-gravatar/templatetags/gravatar.py
dj_gravatar/__init__.py
dj_gravatar/settings.py
dj_gravatar/templatetags/__init__.py
dj_gravatar/templatetags/gravatar.py
dj_gravatar-0.0.2.dist-info/LICENSE
dj_gravatar-0.0.2.dist-info/METADATA
dj_gravatar-0.0.2.dist-info/WHEEL
dj_gravatar-0.0.2.dist-info/top_level.txt
dj_gravatar-0.0.2.dist-info/RECORD
