Metadata-Version: 2.1
Name: dj-gravatar
Version: 0.0.2
Summary: Use Gravatar in a Django Website
Home-page: https://github.com/PhysicistSouravDas/dj-gravatar
Author: Sourav Das
Author-email: souravdas.sd20@gmail.com
License: UNKNOWN
Project-URL: Tracker, https://github.com/PhysicistSouravDas/dj-gravatar/issues
Keywords: django gravatar avatar
Platform: UNKNOWN
Classifier: Development Status :: 3 - Alpha
Classifier: Intended Audience :: Developers
Classifier: License :: OSI Approved :: MIT License
Classifier: Operating System :: OS Independent
Classifier: Framework :: Django :: 2.1
Classifier: Framework :: Django :: 2.2
Classifier: Framework :: Django :: 3.0
Classifier: Framework :: Django :: 3.1
Classifier: Framework :: Django :: 3.2
Classifier: Programming Language :: Python :: 3
Classifier: Programming Language :: Python :: 3.6
Classifier: Programming Language :: Python :: 3.7
Classifier: Programming Language :: Python :: 3.8
Classifier: Programming Language :: Python :: 3.9
Requires-Python: >=3.6
License-File: LICENSE
Requires-Dist: django (>=2.1)
